{"extroversion": "5.8125", "z_extroversion": "0.82874097", "conscientiousness": "4.125", "gender": "2", "z_stability": "-0.157494107", "z_openness": "1.154073273", "z_agreeableness": "0.459638334", "stability": "3.8125", "salience": "1", "name": "Lucy Honeychurch", "poss": [["mother", "mother"], ["feet", "foot"], ["success", "success"], ["room", "room"], ["room", "room"], ["cousin", "cousin"], ["breakfast", "breakfast"], ["day", "day"], ["cousin", "cousin"], ["head", "head"], ["breakfast", "breakfast"], ["friend", "friend"], ["works", "work"], ["mother", "mother"], ["father", "father"], ["eyes", "eye"], ["box", "box"], ["eyes", "eye"], ["Baedeker", "Baedeker"], ["home", "home"], ["way", "way"], ["morning", "morning"], ["grievance", "grievance"], ["heart", "heart"], ["adventures", "adventure"], ["world", "world"], ["desires", "desire"], ["eyes", "eye"], ["well-wishers", "well-wisher"], ["problem", "problem"], ["friends", "friend"], ["eyes", "eye"], ["thoughts", "thought"], ["shopping", "shopping"], ["parasol", "parasol"], ["aim", "aim"], ["perceptions", "perception"], ["cousin", "cousin"], ["thoughts", "thought"], ["life", "life"], ["courage", "courage"], ["manners", "manner"], ["brain", "brain"], ["life", "life"], ["eye", "eye"], ["cousin", "cousin"], ["cousin", "cousin"], ["eyes", "eye"], ["brain", "brain"], ["cousin", "cousin"], ["back", "back"], ["diplomacy", "diplomacy"], ["guard", "guard"], ["emotion", "emotion"], ["sincerity", "sincerity"], ["craving", "craving"], ["chest", "chest"], ["first", "first"], ["brother", "brother"], ["lips", "lip"], ["arms", "arm"], ["cousin", "cousin"], ["praise", "praise"], ["letters", "letter"], ["presence", "presence"], ["tea", "tea"], ["mother", "mother"], ["belief", "belief"], ["outburst", "outburst"], ["vocation", "vocation"], ["brow", "brow"], ["wood", "wood"], ["gentlewomen", "gentlewoman"], ["mother", "mother"], ["antecedents", "antecedent"], ["father", "father"], ["return", "return"], ["environment", "environment"], ["eyes", "eye"], ["heart", "heart"], ["priceless", "priceless"], ["soul", "soul"], ["state", "state"], ["hand", "hand"], ["hand", "hand"], ["feet", "foot"], ["brother", "brother"], ["brother", "brother"], ["lap", "lap"], ["snub", "snub"], ["lover", "lover"], ["brother", "brother"], ["mother", "mother"], ["cousin", "cousin"], ["career", "career"], ["party", "party"], ["son", "son"], ["lips", "lip"], ["room", "room"], ["hand", "hand"], ["cheek", "cheek"], ["hand", "hand"], ["playing", "playing"], ["lover", "lover"], ["mother", "mother"], ["eyes", "eye"], ["own", "own"], ["mother", "mother"], ["mother", "mother"], ["heart", "heart"], ["nerves", "nerve"], ["nerves", "nerve"], ["afternoon", "afternoon"], ["brother", "brother"], ["wails", "wail"], ["tongue", "tongue"], ["cousin", "cousin"], ["mother", "mother"], ["brain", "brain"], ["dress", "dress"], ["look", "look"], ["throat", "throat"], ["finger", "finger"], ["eyes", "eye"], ["time", "time"], ["lip", "lip"], ["mother", "mother"], ["heart", "heart"], ["destination", "destination"], ["photographs", "photograph"], ["cousin", "cousin"], ["reckless", "reckless"], ["voice", "voice"], ["spirits", "spirit"], ["brain", "brain"], ["hand", "hand"], ["cheek", "cheek"], ["soul", "soul"], ["Sabbath", "Sabbath"], ["frock", "frock"], ["stroke", "stroke"], ["room", "room"], ["aim", "aim"], ["brain", "brain"], ["shibboleth", "shibboleth"], ["breakdown", "breakdown"], ["book", "book"], ["cousin", "cousin"], ["admirer", "admirer"], ["eyes", "eye"], ["engagement", "engagement"], ["husband", "husband"], ["mother", "mother"], ["hand", "hand"], ["despondency", "despondency"], ["action", "action"], ["fingers", "finger"], ["hair", "hair"], ["nerves", "nerve"], ["mother", "mother"], ["resolution", "resolution"], ["mother", "mother"], ["Lucy", "Lucy"], ["hands", "hand"], ["bent", "bent"], ["mother", "mother"], ["mother", "mother"], ["soul", "soul"], ["home", "home"], ["brain", "brain"], ["engagement", "engagement"], ["mother", "mother"], ["emotions", "emotion"], ["cue", "cue"], ["mouth", "mouth"], ["teeth", "teeth"], ["point", "point"], ["back", "back"], ["eyes", "eye"], ["affairs", "affair"], ["hands", "hand"], ["ears", "ear"], ["anger", "anger"], ["tears", "tear"], ["breath", "breath"], ["mind", "mind"], ["words", "word"], ["heart", "heart"]], "z_conscientiousness": "-0.447701389", "agent": [["believe", "believe"], ["suppose", "suppose"], ["felt", "felt"], ["insist", "insist"], ["change", "change"], ["acquired", "acquire"], ["rose", "rise"], ["found", "find"], ["rose", "rise"], ["turned", "turn"], ["gave", "give"], ["said", "say"], ["hoping", "hop"], ["do", "do"], ["tried", "try"], ["help", "help"], ["noticed", "notice"], ["committed", "commit"], ["stir", "stir"], ["felt", "felt"], ["entered", "enter"], ["reached", "reach"], ["opened", "open"], ["breathed", "breathe"], ["leaving", "leave"], ["leaning", "lean"], ["listening", "listen"], ["all", "all"], ["like", "like"], ["go", "go"], ["stop", "stop"], ["come", "come"], ["hurried", "hurry"], ["started", "start"], ["inherited", "inherit"], ["followed", "follow"], ["lost", "lose"], ["became", "become"], ["stood", "stand"], ["saw", "saw"], ["thought", "think"], ["seen", "see"], ["waited", "wait"], ["began", "begin"], ["remembered", "remember"], ["descended", "descend"], ["taken", "take"], ["find", "find"], ["find", "find"], ["entered", "enter"], ["realized", "realize"], ["darted", "dart"], ["suggested", "suggest"], ["cried", "cry"], ["came", "come"], ["came", "come"], ["had", "have"], ["ought", "ought"], ["remember", "remember"], ["sympathized", "sympathize"], ["think", "think"], ["found", "find"], ["entered", "enter"], ["opened", "open"], ["longer", "longer"], ["patronizing", "patronize"], ["done", "do"], ["closed", "close"], ["moved", "move"], ["complete", "complete"], ["looked", "look"], ["said", "say"], ["opened", "open"], ["given", "give"], ["said", "say"], ["thought", "think"], ["saw", "saw"], ["think", "think"], ["go", "go"], ["said", "say"], ["want", "want"], ["knew", "know"], ["had", "have"], ["wanted", "want"], ["believed", "believe"], ["attempt", "attempt"], ["stand", "stand"], ["transgress", "transgress"], ["done", "do"], ["like", "like"], ["go", "go"], ["went", "go"], ["stop", "stop"], ["encountered", "encounter"], ["thinking", "think"], ["fidgeted", "fidget"], ["did", "do"], ["repent", "repent"], ["had", "have"], ["unravel", "unravel"], ["take", "take"], ["protest", "protest"], ["poked", "poke"], ["assented", "assent"], ["believed", "believe"], ["intercede", "intercede"], ["knew", "know"], ["had", "have"], ["doubted", "doubt"], ["doubted", "doubt"], ["wished", "wish"], ["defending", "defend"], ["said", "say"], ["stood", "stand"], ["had", "have"], ["sat", "sit"], ["looked", "look"], ["avoided", "avoid"], ["refused", "refuse"], ["disliked", "dislike"], ["know", "know"], ["look", "look"], ["enjoy", "enjoy"], ["lost", "lose"], ["received", "receive"], ["interpret", "interpret"], ["sat", "sit"], ["screamed", "scream"], ["felt", "felt"], ["poured", "pour"], ["became", "become"], ["tried", "try"], ["felt", "felt"], ["dried", "dry"], ["lifted", "lift"], ["thought", "think"], ["made", "make"], ["think", "think"], ["said", "say"], ["think", "think"], ["said", "say"], ["obeyed", "obey"], ["modulate", "modulate"], ["started", "start"], ["began", "begin"], ["gave", "give"], ["felt", "felt"], ["growing", "grow"], ["love", "love"], ["needed", "need"], ["knowing", "know"], ["modified", "modify"], ["embrace", "embrace"], ["said", "say"], ["suffering", "suffer"], ["cried", "cry"], ["want", "want"], ["want", "want"], ["got", "get"], ["said", "say"], ["have", "have"], ["wishes", "wish"], ["seems", "seem"], ["marries", "marry"], ["live", "live"], ["likes", "like"], ["tells", "tell"], ["wrote", "write"], ["tells", "tell"], ["wishes", "wish"], ["seems", "seem"], ["likes", "like"], ["tells", "tell"], ["rose", "rise"], ["moved", "move"], ["smiled", "smile"], ["going", "go"], ["saw", "saw"], ["took", "take"], ["kissed", "kiss"], ["fell", "fell"], ["demanded", "demand"], ["seemed", "seem"], ["herself", "herself"], ["going", "go"], ["want", "want"], ["want", "want"], ["want", "want"], ["spoke", "speak"], ["feigned", "feign"], ["enjoyed", "enjoy"], ["suppose", "suppose"], ["said", "say"], ["missed", "miss"], ["grasped", "grasp"], ["was", "be"], ["flushed", "flush"], ["attended", "attend"], ["looked", "look"], ["followed", "follow"], ["said", "say"], ["wonder", "wonder"], ["startled", "startle"], ["standing", "stand"], ["rebuked", "rebuke"], ["permitted", "permit"], ["revered", "revere"], ["realized", "realize"], ["consecrated", "consecrate"], ["reached", "reach"], ["was", "be"], ["loved", "love"], ["trying", "try"], ["fell", "fell"], ["nursing", "nurse"], ["sitting", "sit"], ["see", "see"], ["believed", "believe"], ["borne", "bear"], ["screech", "screech"], ["heard", "hear"], ["asked", "ask"], ["is", "be"], ["remained", "remain"], ["was", "be"], ["met", "meet"], ["was", "be"], ["thought", "think"], ["minded", "mind"], ["longed", "long"], ["said", "say"], ["join", "join"], ["told", "tell"], ["saw", "saw"], ["loved", "love"], ["gone", "go"], ["spoke", "speak"], ["becoming", "become"], ["ring", "ring"], ["liked", "like"], ["found", "find"], ["returned", "return"], ["used", "use"], ["read", "read"], ["rehearsed", "rehearse"], ["meet", "meet"], ["imagined", "imagine"], ["imagined", "imagine"], ["soothed", "soothe"], ["tinkered", "tinker"], ["regarded", "regard"], ["applied", "apply"], ["disliked", "dislike"], ["faltered", "falter"], ["mastered", "master"], ["dazzled", "dazzle"], ["bewildered", "bewilder"], ["wished", "wish"], ["knew", "know"], ["remember", "remember"], ["said", "say"], ["have", "have"], ["felt", "felt"], ["saw", "saw"], ["said", "say"], ["said", "say"], ["fed", "feed"], ["is", "be"], ["want", "want"], ["makes", "make"], ["hardened", "harden"], ["faced", "face"], ["faced", "face"], ["gazed", "gaze"], ["put", "put"], ["talked", "talk"], ["wished", "wish"], ["wished", "wish"], ["suffered", "suffer"], ["know", "know"], ["said", "say"], ["am", "be"], ["tripped", "trip"], ["paused", "pause"], ["thought", "think"], ["paused", "pause"], ["saw", "saw"], ["thought", "think"], ["escaped", "escape"], ["steps", "step"], ["frowns", "frown"], ["frown", "frown"], ["measure", "measure"], ["picked", "pick"], ["glanced", "glance"], ["read", "read"], ["knew", "know"], ["thought", "think"], ["knew", "know"], ["found", "find"], ["forgotten", "forget"], ["confused", "confuse"], ["bit", "bite"], ["want", "want"], ["know", "know"], ["ignored", "ignore"], ["introduced", "introduce"], ["going", "go"], ["said", "say"], ["suspected", "suspect"], ["known", "know"], ["remembered", "remember"], ["surmised", "surmise"], ["caught", "catch"], ["said", "say"], ["do", "do"], ["went", "go"], ["murmured", "murmur"], ["knew", "know"], ["sighted", "sight"], ["greeted", "greet"], ["gone", "go"], ["raised", "raise"], ["know", "know"], ["wanted", "want"], ["played", "play"], ["stopped", "stop"], ["go", "go"], ["change", "change"], ["kept", "keep"], ["broke", "break"], ["changed", "change"], ["wondered", "wonder"], ["overhaul", "overhaul"], ["settle", "settle"], ["married", "marry"], ["recollected", "recollect"], ["publishing", "publish"], ["developed", "develop"], ["said", "say"], ["went", "go"], ["coming", "come"], ["write", "write"], ["prepared", "prepare"], ["returned", "return"], ["conquered", "conquer"], ["forgot", "forget"], ["compelled", "compel"], ["encouraged", "encourage"], ["put", "put"], ["know", "know"], ["said", "say"], ["see", "see"], ["want", "want"], ["said", "say"], ["said", "say"], ["speak", "speak"], ["realized", "realize"], ["said", "say"], ["give", "give"], ["explain", "explain"], ["marrying", "marry"], ["had", "have"], ["said", "say"], ["think", "think"], ["stood", "stand"], ["broke", "break"], ["knew", "know"], ["said", "say"], ["known", "know"], ["feeling", "feel"], ["felt", "felt"], ["developed", "develop"], ["are", "be"], ["think", "think"], ["see", "see"], ["speak", "speak"], ["will", "will"], ["said", "say"], ["entered", "enter"], ["pretended", "pretend"], ["love", "love"], ["pretended", "pretend"], ["loved", "love"], ["enjoy", "enjoy"], ["see", "see"], ["see", "see"], ["dressed", "dress"], ["see", "see"], ["play", "play"], ["did", "do"], ["marry", "marry"], ["pursuing", "pursue"], ["stopped", "stop"], ["marching", "march"], ["wish", "wish"], ["go", "go"], ["have", "have"], ["ran", "run"], ["HAVE", "HAVE"], ["realize", "realize"], ["want", "want"], ["wanted", "want"], ["want", "want"], ["confirm", "confirm"], ["carried", "carry"], ["tell", "tell"], ["sat", "sit"], ["want", "want"], ["had", "have"], ["talk", "talk"], ["thank", "thank"], ["like", "like"], ["had", "have"], ["described", "describe"], ["felt", "felt"], ["borrowed", "borrow"], ["drifting", "drift"], ["given", "give"], ["say", "say"], ["disliked", "dislike"], ["deemed", "deem"], ["hoped", "hop"], ["escaped", "escape"], ["discovered", "discover"], ["acknowledge", "acknowledge"], ["disordering", "disorder"], ["felt", "felt"], ["love", "love"], ["broke", "break"], ["love", "love"], ["go", "go"], ["love", "love"], ["look", "look"], ["help", "help"], ["felt", "felt"], ["proceeded", "proceed"], ["determined", "determine"], ["seen", "see"], ["felt", "felt"], ["seen", "see"], ["share", "share"], ["want", "want"], ["said", "say"], ["knew", "know"], ["wanted", "want"], ["tried", "try"], ["screwed", "screw"], ["said", "say"], ["spoke", "speak"], ["clenched", "clench"], ["wish", "wish"], ["complained", "complain"], ["wrestled", "wrestle"], ["squirted", "squirt"], ["see", "see"], ["missed", "miss"], ["sank", "sink"], ["got", "get"], ["turned", "turn"], ["began", "begin"], ["selected", "select"], ["said", "say"], ["have", "have"], ["did", "do"], ["suggested", "suggest"], ["said", "say"], ["tell", "tell"], ["mean", "mean"], ["began", "begin"], ["remembered", "remember"], ["rejected", "reject"], ["said", "say"], ["mean", "mean"], ["murmured", "murmur"], ["said", "say"]], "agreeableness": "5.125", "openness": "6.375", "patient": [["said", "say"], ["put", "put"], ["enjoy", "enjoy"], ["enabled", "enable"], ["accompany", "accompany"], ["take", "take"], ["said", "say"], ["exclaimed", "exclaim"], ["followed", "follow"], ["dragged", "drag"], ["worried", "worry"], ["jilted", "jilt"], ["persuading", "persuade"], ["lead", "lead"], ["did", "do"], ["said", "say"], ["made", "make"], ["said", "say"], ["annex", "annex"], ["interest", "interest"], ["annoyed", "annoy"], ["warned", "warn"], ["seen", "see"], ["oppressed", "oppress"], ["had", "have"], ["frightened", "frighten"], ["love", "love"], ["frightened", "frighten"], ["feel", "feel"], ["addressed", "address"], ["poured", "pour"], ["love", "love"], ["needed", "need"], ["married", "marry"], ["kissed", "kiss"], ["known", "know"], ["introduce", "introduce"], ["dragged", "drag"], ["said", "say"], ["said", "say"], ["roused", "rouse"], ["pulled", "pull"], ["leave", "leave"], ["took", "take"], ["entitled", "entitle"], ["satisfy", "satisfy"], ["asked", "ask"], ["estrange", "estrange"], ["Make", "Make"], ["teaching", "teach"], ["had", "have"], ["greet", "greet"], ["repeated", "repeat"], ["encompassed", "encompass"], ["moved", "move"], ["convince", "convince"], ["replied", "reply"], ["overhaul", "overhaul"], ["said", "say"], ["claimed", "claim"], ["pleased", "please"], ["love", "love"], ["kept", "keep"], ["broke", "break"], ["overhaul", "overhaul"], ["said", "say"], ["recollected", "recollect"], ["defeat", "defeat"], ["compelled", "compel"], ["wanted", "want"], ["help", "help"], ["speak", "speak"], ["amuses", "amuse"], ["fitted", "fit"], ["received", "receive"], ["cried", "cry"], ["Do", "Do"], ["help", "help"], ["place", "place"], ["help", "help"], ["tell", "tell"], ["heard", "hear"], ["see", "see"], ["bothering", "bother"], ["said", "say"], ["gasped", "gasp"]], "mod": [["selfish", "selfish"], ["pleased", "pleased"], ["ready", "ready"], ["delighted", "delighted"], ["Florence", "Florence"], ["spirits", "spirit"], ["full", "full"], ["sure", "sure"], ["conscious", "conscious"], ["sure", "sure"], ["deferential", "deferential"], ["parishioner", "parishioner"], ["system", "system"], ["sorry", "sorry"], ["restive", "restive"], ["ready", "ready"], ["frightened", "frightened"], ["frightened", "frightened"], ["same", "same"], ["safe", "safe"], ["slow", "slow"], ["power", "power"], ["gaunt", "gaunt"], ["clay", "clay"], ["shy", "shy"], ["slow", "slow"], ["enough", "enough"], ["alive", "alive"], ["sure", "sure"], ["affair", "affair"], ["great", "great"], ["great", "great"], ["first", "first"], ["matter", "matter"], ["nervous", "nervous"], ["obvious", "obvious"], ["glad", "glad"], ["nature", "nature"], ["able", "able"], ["quick", "quick"], ["mad", "mad"], ["inclined", "inclined"], ["sorry", "sorry"], ["hopeless", "hopeless"], ["conscious", "conscious"], ["glad", "glad"], ["singing", "singing"], ["tack", "tack"], ["silent", "silent"]], "valence": "1"}