{"conscientiousness": "4", "patient": [["conducting", "conduct", "VBG"], ["must", "must", "MD"], ["thank", "thank", "VBP"], ["think", "think", "VBP"]], "z_stability": "-0.353431352", "poss": [["spirit", "spirit", "NN"], ["vengeance", "vengeance", "NN"], ["pilgrimage", "pilgrimage", "NN"], ["woes", "woe", "NNS"], ["heart", "heart", "NN"], ["father", "father", "NN"], ["intentions", "intention", "NNS"], ["happiness", "happiness", "NN"]], "agent": [["do", "do", "VBP"], ["dare", "dare", "VB"], ["undergone", "undergo", "VBN"], ["hover", "hover", "VB"], ["direct", "direct", "VB"], ["speak", "speak", "VBP"], ["expressed", "express", "VBD"]], "mod": [["selfish", "selfish", "JJ"], ["dead", "dead", "JJ"]], "extroversion": "6.5", "stability": "3.5", "valence": "1", "gender": "1", "name": "Robert Walton", "salience": "1", "agreeableness": "4", "z_openness": "0.926158885", "z_conscientiousness": "-0.519299483", "z_extroversion": "1.215049568", "z_agreeableness": "-0.127153484", "openness": "6"}