{"conscientiousness": "6.266333333", "patient": [["suppose", "suppose", "VB"], ["meet", "meet", "VB"], ["said", "say", "VBD"], ["Invite", "Invite", "VB"], ["help", "help", "VB"], ["leave", "leave", "VBP"], ["brought", "bring", "VBD"], ["give", "give", "VB"], ["leave", "leave", "VB"], ["exclaimed", "exclaim", "VBD"]], "z_stability": "0.921048987", "poss": [["inquiries", "inquiry", "NNS"], ["head", "head", "NN"], ["wife", "wife", "NN"], ["solitude", "solitude", "NN"], ["daughter", "daughter", "NN"], ["mind", "mind", "NN"], ["daughter", "daughter", "NN"], ["civility", "civility", "NN"], ["short", "short", "JJ"], ["pretensions", "pretension", "NNS"], ["looks", "look", "NNS"]], "agent": [["lived", "live", "VBD"], ["returned", "return", "VBN"], ["walked", "walk", "VBD"], ["had", "have", "VBD"], ["loves", "love", "VBZ"], ["flatter", "flatter", "VBD"], ["said", "say", "VBD"], ["meant", "mean", "VBD"], ["shook", "shake", "VBD"], ["be", "be", "VB"], ["thought", "think", "VBD"], ["foretell", "foretell", "VB"], ["made", "make", "VBN"], ["had", "have", "VBD"], ["called", "call", "VBD"], ["sat", "sit", "VBD"], ["made", "make", "VBN"], ["had", "have", "VBD"], ["offering", "offer", "VBG"], ["take", "take", "VB"], ["said", "say", "VBD"], ["know", "know", "VBP"], ["know", "know", "VBP"], ["think", "think", "VB"], ["say", "say", "VB"], ["would", "would", "MD"], ["observed", "observe", "VBN"], ["spoken", "speak", "VBN"], ["had", "have", "VBD"], ["wished", "wish", "VBD"], ["knew", "know", "VBD"], ["make", "make", "VB"], ["saw", "saw", "VBD"], ["quarrel", "quarrel", "VB"], ["came", "come", "VBD"]], "mod": [["friend", "friend", "NN"], ["good", "good", "JJ"], ["man", "man", "NN"], ["situation", "situation", "NN"], ["displeased", "displeased", "JJ"]], "extroversion": "3.6", "stability": "5.532666667", "valence": "1", "gender": "1", "name": "George Knightley", "salience": "2", "agreeableness": "4.766666667", "z_openness": "-0.046275836", "z_conscientiousness": "0.778821697", "z_extroversion": "-0.41447034", "z_agreeableness": "0.272734274", "openness": "4.4"}