{"conscientiousness": "6", "patient": [["prevented", "prevent", "VBD"], ["hurt", "hurt", "VB"]], "z_stability": "-0.980430534", "poss": [["claim", "claim", "NN"], ["profession", "profession", "NN"], ["character", "character", "NN"], ["temper", "temper", "NN"], ["perfection", "perfection", "NN"]], "agent": [["do", "do", "VB"], ["promises", "promise", "VBZ"], ["was", "be", "VBD"], ["had", "have", "VBD"], ["act", "act", "VB"], ["say", "say", "VB"]], "mod": [["town", "town", "NN"], ["man", "man", "NN"]], "extroversion": "2", "stability": "2.5", "valence": "1", "gender": "1", "name": "John Knightley", "salience": "2", "agreeableness": "2.5", "z_openness": "-1.504927917", "z_conscientiousness": "0.626270024", "z_extroversion": "-1.313515806", "z_agreeableness": "-0.909542574", "openness": "2"}