{"poss": [["loss", "loss", "NN"], ["kindness", "kindness", "NN"], ["powers", "power", "NNS"], ["own", "own", "JJ"], ["will", "will", "NN"], ["brother", "brother", "NN"], ["home", "home", "NN"], ["marriage", "marriage", "NN"]], "z_openness": "0.014501334", "salience": "2", "z_extroversion": "-0.189708973", "patient": [["attach", "attach", "VB"], ["nursed", "nurse", "VBD"], ["had", "have", "VBN"], ["marry", "marry", "VB"], ["persuade", "persuade", "VB"]], "openness": "4.5", "z_conscientiousness": "0.626270024", "extroversion": "4", "gender": "2", "agent": [["married", "marry", "VBN"], ["recalled", "recall", "VBD"], ["taught", "teach", "VBN"], ["played", "play", "VBN"], ["devoted", "devote", "VBN"], ["have", "have", "VB"], ["have", "have", "VB"], ["ought", "ought", "MD"], ["had", "have", "VBD"], ["had", "have", "VBD"], ["best", "best", "JJS"], ["had", "have", "VBD"], ["received", "receive", "VBN"], ["formed", "form", "VBD"], ["felt", "felt", "VBD"], ["lived", "live", "VBN"], ["know", "know", "VB"], ["said", "say", "VBD"], ["think", "think", "VBP"], ["failed", "fail", "VBD"], ["said", "say", "VBD"], ["wish", "wish", "VB"], ["recommend", "recommend", "VB"], ["mean", "mean", "VBP"], ["assure", "assure", "VBP"]], "agreeableness": "6", "name": "Mrs. Weston (Previously Miss Taylor)", "z_agreeableness": "0.91603197", "z_stability": "0.587067423", "valence": "1", "mod": [["gainer", "gainer", "NN"], ["enough", "enough", "JJ"], ["woman", "woman", "NN"], ["object", "object", "NN"]], "stability": "5", "conscientiousness": "6"}