{"conscientiousness": "7", "patient": [["says", "say", "VBZ"], ["asked", "ask", "VBD"], ["addressing", "address", "VBG"], ["addressing", "address", "VBG"], ["addressed", "address", "VBD"], ["liked", "like", "VBD"], ["circumvent", "circumvent", "VB"], ["amused", "amuse", "VBD"], ["showed", "show", "VBD"], ["told", "tell", "VBN"], ["enlighten", "enlighten", "VB"], ["take", "take", "VB"], ["pressing", "press", "VBG"], ["take", "take", "VB"], ["joined", "join", "VBD"], ["bring", "bring", "VB"], ["found", "find", "VBD"], ["help", "help", "VB"], ["condemned", "condemn", "VBN"], ["interrupted", "interrupt", "VBD"], ["show", "show", "VB"], ["Tell", "Tell", "VB"], ["calling", "call", "VBG"], ["believed", "believe", "VBN"], ["telling", "tell", "VBG"]], "z_stability": "1.841065788", "poss": [["tastes", "taste", "NNS"], ["time", "time", "NN"], ["brother-officer", "brother-officer", "NN"], ["head", "head", "NN"], ["brother-officer", "brother-officer", "NN"], ["eyes", "eye", "NNS"], ["business", "business", "NN"], ["acknowledgments", "acknowledgment", "NNS"], ["views", "view", "NNS"], ["face", "face", "NN"], ["hands", "hand", "NNS"], ["pockets", "pocket", "NNS"], ["penknife", "penknife", "NN"], ["thoughts", "thought", "NNS"], ["eyes", "eye", "NNS"], ["spirits", "spirit", "NNS"], ["opinion", "opinion", "NN"], ["boots", "boot", "NNS"], ["suspicions", "suspicion", "NNS"], ["examination", "examination", "NN"], ["point", "point", "NN"], ["knees", "knee", "NNS"], ["prayers", "prayer", "NNS"], ["inquiries", "inquiry", "NNS"], ["logic", "logic", "NN"], ["stomach", "stomach", "NN"], ["spirits", "spirit", "NNS"], ["shot", "shot", "NN"], ["nip", "nip", "NN"], ["hand", "hand", "NN"], ["estimation", "estimation", "NN"], ["arm", "arm", "NN"], ["face", "face", "NN"], ["glory", "glory", "NN"], ["investigations", "investigation", "NNS"], ["character", "character", "NN"], ["purpose", "purpose", "NN"], ["way", "way", "NN"], ["inquiries", "inquiry", "NNS"], ["time", "time", "NN"], ["interest", "interest", "NN"], ["servant", "servant", "JJ"], ["return", "return", "NN"], ["friend", "friend", "NN"], ["enemy", "enemy", "NN"], ["roses", "rose", "NNS"], ["examination", "examination", "NN"], ["employer", "employer", "NN"], ["inquiry", "inquiry", "NN"], ["voice", "voice", "NN"]], "agent": [["Cuff", "Cuff", "NNP"], ["looked", "look", "VBD"], ["spied", "spy", "VBD"], ["walked", "walk", "VBD"], ["shown", "show", "VBN"], ["have", "have", "VBP"], ["says", "say", "VBZ"], ["says", "say", "VBZ"], ["thought", "think", "VBD"], ["put", "put", "VBD"], ["asked", "ask", "VBD"], ["looked", "look", "VBD"], ["looked", "look", "VBN"], ["sighed", "sigh", "VBN"], ["shook", "shake", "VBD"], ["said", "say", "VBD"], ["gave", "give", "VBD"], ["addressed", "address", "VBD"], ["Cuff", "Cuff", "NNP"], ["said", "say", "VBD"], ["formed", "form", "VBN"], ["says", "say", "VBZ"], ["beg", "beg", "VBP"], ["discovered", "discover", "VBN"], ["decided", "decide", "VBN"], ["got", "get", "VBN"], ["said", "say", "VBD"], ["propose", "propose", "VBP"], ["made", "make", "VBD"], ["beg", "beg", "VBP"], ["said", "say", "VBD"], ["like", "like", "VB"], ["want", "want", "VBP"], ["added", "add", "VBD"], ["made", "make", "VBD"], ["turned", "turn", "VBD"], ["put", "put", "VBD"], ["whistled", "whistle", "VBD"], ["finished", "finish", "VBD"], ["looked", "look", "VBD"], ["put", "put", "VBD"], ["say", "say", "VB"], ["laughed", "laugh", "VBD"], ["curled", "curl", "VBD"], ["curled", "curl", "VBD"], ["believe", "believe", "VB"], ["keep", "keep", "VB"], ["ought", "ought", "MD"], ["has", "have", "VBZ"], ["cut", "cut", "VB"], ["found", "find", "VBN"], ["eyed", "eye", "VBN"], ["shown", "show", "VBN"], ["believe", "believe", "VB"], ["said", "say", "VBD"], ["says", "say", "VBZ"], ["saw", "saw", "VBD"], ["admired", "admire", "VBD"], ["had", "have", "VBD"], ["decided", "decide", "VBD"], ["give", "give", "VB"], ["came", "come", "VBD"], ["know", "know", "VBP"], ["suggesting", "suggest", "VBG"], ["go", "go", "VB"], ["went", "go", "VBD"], ["sat", "sit", "VBD"], ["asked", "ask", "VBD"], ["follow", "follow", "VB"], ["says", "say", "VBZ"], ["find", "find", "VB"], ["says", "say", "VBZ"], ["stopped", "stop", "VBD"], ["laid", "lay", "VBD"], ["walked", "walk", "VBD"], ["went", "go", "VBD"], ["looking", "look", "VBG"], ["looked", "look", "VBD"], ["suspect", "suspect", "VB"], ["said", "say", "VBD"], ["know", "know", "VBP"], ["Solomon", "Solomon", "NNP"], ["told", "tell", "VBN"], ["do", "do", "VBP"], ["said", "say", "VBD"], ["look", "look", "VB"], ["went", "go", "VBD"], ["knew", "know", "VBD"], ["expect", "expect", "VB"], ["looked", "look", "VBD"], ["condemned", "condemn", "VBN"], ["put", "put", "VBD"], ["heard", "hear", "VBN"], ["suspect", "suspect", "VB"], ["laid", "lay", "VBD"], ["confuse", "confuse", "VB"], ["irritate", "irritate", "VB"], ["daunt", "daunt", "VB"], ["left", "leave", "VBN"], ["discovered", "discover", "VBD"], ["discovered", "discover", "VBD"], ["thought", "think", "VBD"], ["saw", "saw", "VBD"], ["wrapped", "wrap", "VBD"], ["rejoined", "rejoin", "VBD"], ["say", "say", "VBP"], ["hear", "hear", "VB"], ["started", "start", "VBN"], ["left", "leave", "VBN"], ["was", "be", "VBD"], ["be", "be", "VB"], ["Ireland", "Ireland", "NNP"], ["hold", "hold", "VB"], ["said", "say", "VBD"], ["agree", "agree", "VBP"], ["rose", "rise", "VBD"], ["went", "go", "VBD"], ["came", "come", "VBD"], ["talked", "talk", "VBD"], ["asked", "ask", "VBD"], ["got", "get", "VBN"], ["appear", "appear", "VB"], ["went", "go", "VBD"], ["came", "come", "VBD"], ["said", "say", "VBD"], ["tell", "tell", "VB"], ["am", "be", "VBP"], ["met", "meet", "VBD"]], "mod": [["Cuff", "Cuff", "NN"], ["work", "work", "NN"], ["gentleman", "gentleman", "NN"], ["much", "much", "JJ"], ["man", "man", "NN"], ["trouble", "trouble", "NN"], ["character", "character", "NN"], ["way", "way", "NN"], ["to-night", "to-night", "NN"], ["boy", "boy", "NN"], ["Cuff", "Cuff", "NN"]], "extroversion": "1", "stability": "7", "valence": "1", "gender": "1", "name": "Sergeant Cuff", "salience": "1", "agreeableness": "4", "z_openness": "0.926158885", "z_conscientiousness": "1.199054778", "z_extroversion": "-1.875419223", "z_agreeableness": "-0.127153484", "openness": "6"}